{
	"completely_empty": false,
	"image": {
		"height": 480,
		"scale": 1.4479166666666667,
		"width": 393
	},
	"mark": [
		{
			"class_idx": 0,
			"name": "license-plate",
			"points": [
				{
					"int_x": 220,
					"int_y": 92,
					"x": 0.5603053435500001,
					"y": 0.19187500005000002
				},
				{
					"int_x": 289,
					"int_y": 92,
					"x": 0.73435114505,
					"y": 0.19187500005000002
				},
				{
					"int_x": 289,
					"int_y": 146,
					"x": 0.73435114505,
					"y": 0.30395833335
				},
				{
					"int_x": 220,
					"int_y": 146,
					"x": 0.5603053435500001,
					"y": 0.30395833335
				}
			],
			"rect": {
				"h": 0.11208333329999998,
				"int_h": 55,
				"int_w": 70,
				"int_x": 220,
				"int_y": 92,
				"w": 0.17404580149999993,
				"x": 0.5603053435500001,
				"y": 0.19187500005000002
			}
		}
	],
	"timestamp": 1722547421,
	"version": "1.8.27-1"
}
