{
	"completely_empty": false,
	"image": {
		"height": 748,
		"scale": 0.929144385026738,
		"width": 381
	},
	"mark": [
		{
			"class_idx": 0,
			"name": "license-plate",
			"points": [
				{
					"int_x": 157,
					"int_y": 92,
					"x": 0.4112860892,
					"y": 0.12232620325000002
				},
				{
					"int_x": 199,
					"int_y": 92,
					"x": 0.5230971128,
					"y": 0.12232620325000002
				},
				{
					"int_x": 199,
					"int_y": 162,
					"x": 0.5230971128,
					"y": 0.21671122995
				},
				{
					"int_x": 157,
					"int_y": 162,
					"x": 0.4112860892,
					"y": 0.21671122995
				}
			],
			"rect": {
				"h": 0.09438502669999999,
				"int_h": 71,
				"int_w": 43,
				"int_x": 157,
				"int_y": 92,
				"w": 0.11181102360000006,
				"x": 0.4112860892,
				"y": 0.12232620325000002
			}
		}
	],
	"timestamp": 1722547423,
	"version": "1.8.27-1"
}
