{
	"completely_empty": false,
	"image": {
		"height": 692,
		"scale": 1.004335260115607,
		"width": 687
	},
	"mark": [
		{
			"class_idx": 0,
			"name": "license-plate",
			"points": [
				{
					"int_x": 242,
					"int_y": 532,
					"x": 0.35181950505000004,
					"y": 0.76835260115
				},
				{
					"int_x": 304,
					"int_y": 532,
					"x": 0.44235807855,
					"y": 0.76835260115
				},
				{
					"int_x": 304,
					"int_y": 558,
					"x": 0.44235807855,
					"y": 0.80621387285
				},
				{
					"int_x": 242,
					"int_y": 558,
					"x": 0.35181950505000004,
					"y": 0.80621387285
				}
			],
			"rect": {
				"h": 0.03786127169999998,
				"int_h": 27,
				"int_w": 63,
				"int_x": 242,
				"int_y": 532,
				"w": 0.09053857349999994,
				"x": 0.35181950505000004,
				"y": 0.76835260115
			}
		}
	],
	"timestamp": 1722547422,
	"version": "1.8.27-1"
}
