{
	"completely_empty": false,
	"image": {
		"height": 1600,
		"scale": 0.434375,
		"width": 1600
	},
	"mark": [
		{
			"class_idx": 0,
			"name": "license-plate",
			"points": [
				{
					"int_x": 131,
					"int_y": 158,
					"x": 0.08201438848920867,
					"y": 0.09856115107913666
				},
				{
					"int_x": 1324,
					"int_y": 158,
					"x": 0.8273381294964028,
					"y": 0.09856115107913666
				},
				{
					"int_x": 1324,
					"int_y": 1127,
					"x": 0.8273381294964028,
					"y": 0.7043165467625899
				},
				{
					"int_x": 131,
					"int_y": 1127,
					"x": 0.08201438848920867,
					"y": 0.7043165467625899
				}
			],
			"rect": {
				"h": 0.6057553956834533,
				"int_h": 970,
				"int_w": 1194,
				"int_x": 131,
				"int_y": 158,
				"w": 0.7453237410071942,
				"x": 0.08201438848920867,
				"y": 0.09856115107913666
			}
		}
	],
	"timestamp": 1722545918,
	"version": "1.8.27-1"
}
