{
	"completely_empty": false,
	"image": {
		"height": 1187,
		"scale": 0.5855096882898062,
		"width": 876
	},
	"mark": [
		{
			"class_idx": 0,
			"name": "license-plate",
			"points": [
				{
					"int_x": 291,
					"int_y": 391,
					"x": 0.33237410074999996,
					"y": 0.32908704884999995
				},
				{
					"int_x": 541,
					"int_y": 391,
					"x": 0.61726618705,
					"y": 0.32908704884999995
				},
				{
					"int_x": 541,
					"int_y": 713,
					"x": 0.61726618705,
					"y": 0.60084925695
				},
				{
					"int_x": 291,
					"int_y": 713,
					"x": 0.33237410074999996,
					"y": 0.60084925695
				}
			],
			"rect": {
				"h": 0.27176220810000007,
				"int_h": 323,
				"int_w": 251,
				"int_x": 291,
				"int_y": 391,
				"w": 0.28489208630000007,
				"x": 0.33237410074999996,
				"y": 0.32908704884999995
			}
		}
	],
	"timestamp": 1722547477,
	"version": "1.8.27-1"
}
