{
	"completely_empty": false,
	"image": {
		"height": 1200,
		"scale": 0.5791666666666667,
		"width": 1600
	},
	"mark": [
		{
			"class_idx": 0,
			"name": "license-plate",
			"points": [
				{
					"int_x": 68,
					"int_y": 270,
					"x": 0.04261057174999999,
					"y": 0.22517985615000002
				},
				{
					"int_x": 1523,
					"int_y": 270,
					"x": 0.95199568505,
					"y": 0.22517985615000002
				},
				{
					"int_x": 1523,
					"int_y": 918,
					"x": 0.95199568505,
					"y": 0.76474820145
				},
				{
					"int_x": 68,
					"int_y": 918,
					"x": 0.04261057174999999,
					"y": 0.76474820145
				}
			],
			"rect": {
				"h": 0.5395683453,
				"int_h": 649,
				"int_w": 1456,
				"int_x": 68,
				"int_y": 270,
				"w": 0.9093851132999999,
				"x": 0.04261057174999999,
				"y": 0.22517985615000002
			}
		}
	],
	"timestamp": 1722547474,
	"version": "1.8.27-1"
}
