{
	"completely_empty": false,
	"image": {
		"height": 194,
		"scale": 3.582474226804124,
		"width": 259
	},
	"mark": [
		{
			"class_idx": 0,
			"name": "license-plate",
			"points": [
				{
					"int_x": 44,
					"int_y": 19,
					"x": 0.16918103448275856,
					"y": 0.09640287769784173
				},
				{
					"int_x": 220,
					"int_y": 19,
					"x": 0.8480603448275862,
					"y": 0.09640287769784173
				},
				{
					"int_x": 220,
					"int_y": 168,
					"x": 0.8480603448275862,
					"y": 0.8676258992805755
				},
				{
					"int_x": 44,
					"int_y": 168,
					"x": 0.16918103448275856,
					"y": 0.8676258992805755
				}
			],
			"rect": {
				"h": 0.7712230215827338,
				"int_h": 150,
				"int_w": 177,
				"int_x": 44,
				"int_y": 19,
				"w": 0.6788793103448276,
				"x": 0.16918103448275856,
				"y": 0.09640287769784173
			}
		}
	],
	"timestamp": 1721783171,
	"version": "1.8.27-1"
}
