{
	"completely_empty": false,
	"image": {
		"height": 194,
		"scale": 3.582474226804124,
		"width": 259
	},
	"mark": [
		{
			"class_idx": 0,
			"name": "license-plate",
			"points": [
				{
					"int_x": 18,
					"int_y": 46,
					"x": 0.07058189655172414,
					"y": 0.2388489208633094
				},
				{
					"int_x": 228,
					"int_y": 46,
					"x": 0.8798491379310345,
					"y": 0.2388489208633094
				},
				{
					"int_x": 228,
					"int_y": 142,
					"x": 0.8798491379310345,
					"y": 0.7309352517985612
				},
				{
					"int_x": 18,
					"int_y": 142,
					"x": 0.07058189655172414,
					"y": 0.7309352517985612
				}
			],
			"rect": {
				"h": 0.49208633093525184,
				"int_h": 97,
				"int_w": 211,
				"int_x": 18,
				"int_y": 46,
				"w": 0.8092672413793103,
				"x": 0.07058189655172414,
				"y": 0.2388489208633094
			}
		}
	],
	"timestamp": 1721783094,
	"version": "1.8.27-1"
}
