{
	"completely_empty": false,
	"image": {
		"height": 756,
		"scale": 0.7867518884369552,
		"width": 1721
	},
	"mark": [
		{
			"class_idx": 0,
			"name": "license-plate",
			"points": [
				{
					"int_x": 51,
					"int_y": 120,
					"x": 0.0295177222,
					"y": 0.1592592593
				},
				{
					"int_x": 98,
					"int_y": 120,
					"x": 0.0567112144,
					"y": 0.1592592593
				},
				{
					"int_x": 98,
					"int_y": 146,
					"x": 0.0567112144,
					"y": 0.1936507937
				},
				{
					"int_x": 51,
					"int_y": 146,
					"x": 0.0295177222,
					"y": 0.1936507937
				}
			],
			"rect": {
				"h": 0.03439153439999998,
				"int_h": 27,
				"int_w": 48,
				"int_x": 51,
				"int_y": 120,
				"w": 0.027193492200000002,
				"x": 0.0295177222,
				"y": 0.1592592593
			}
		},
		{
			"class_idx": 0,
			"name": "license-plate",
			"points": [
				{
					"int_x": 201,
					"int_y": 207,
					"x": 0.1170249855,
					"y": 0.2740740741
				},
				{
					"int_x": 226,
					"int_y": 207,
					"x": 0.1314352121,
					"y": 0.2740740741
				},
				{
					"int_x": 226,
					"int_y": 218,
					"x": 0.1314352121,
					"y": 0.28888888890000003
				},
				{
					"int_x": 201,
					"int_y": 218,
					"x": 0.1170249855,
					"y": 0.28888888890000003
				}
			],
			"rect": {
				"h": 0.01481481480000002,
				"int_h": 12,
				"int_w": 26,
				"int_x": 201,
				"int_y": 207,
				"w": 0.014410226600000006,
				"x": 0.1170249855,
				"y": 0.2740740741
			}
		},
		{
			"class_idx": 0,
			"name": "license-plate",
			"points": [
				{
					"int_x": 580,
					"int_y": 234,
					"x": 0.33695525860000003,
					"y": 0.30925925925000003
				},
				{
					"int_x": 609,
					"int_y": 234,
					"x": 0.3540383498,
					"y": 0.30925925925000003
				},
				{
					"int_x": 609,
					"int_y": 247,
					"x": 0.3540383498,
					"y": 0.32619047615
				},
				{
					"int_x": 580,
					"int_y": 247,
					"x": 0.33695525860000003,
					"y": 0.32619047615
				}
			],
			"rect": {
				"h": 0.01693121689999999,
				"int_h": 14,
				"int_w": 30,
				"int_x": 580,
				"int_y": 234,
				"w": 0.017083091199999956,
				"x": 0.33695525860000003,
				"y": 0.30925925925000003
			}
		},
		{
			"class_idx": 0,
			"name": "license-plate",
			"points": [
				{
					"int_x": 925,
					"int_y": 244,
					"x": 0.53765252755,
					"y": 0.32301587305
				},
				{
					"int_x": 949,
					"int_y": 244,
					"x": 0.5517141196500001,
					"y": 0.32301587305
				},
				{
					"int_x": 949,
					"int_y": 251,
					"x": 0.5517141196500001,
					"y": 0.33253968255
				},
				{
					"int_x": 925,
					"int_y": 251,
					"x": 0.53765252755,
					"y": 0.33253968255
				}
			],
			"rect": {
				"h": 0.00952380949999998,
				"int_h": 8,
				"int_w": 25,
				"int_x": 925,
				"int_y": 244,
				"w": 0.01406159210000002,
				"x": 0.53765252755,
				"y": 0.32301587305
			}
		}
	],
	"timestamp": 1722547394,
	"version": "1.8.27-1"
}
