{
	"completely_empty": false,
	"image": {
		"height": 936,
		"scale": 0.7425213675213675,
		"width": 1772
	},
	"mark": [
		{
			"class_idx": 0,
			"name": "license-plate",
			"points": [
				{
					"int_x": 877,
					"int_y": 136,
					"x": 0.49503386000000005,
					"y": 0.1451923077
				},
				{
					"int_x": 977,
					"int_y": 136,
					"x": 0.5514672686000001,
					"y": 0.1451923077
				},
				{
					"int_x": 977,
					"int_y": 171,
					"x": 0.5514672686000001,
					"y": 0.18215811969999998
				},
				{
					"int_x": 877,
					"int_y": 171,
					"x": 0.49503386000000005,
					"y": 0.18215811969999998
				}
			],
			"rect": {
				"h": 0.03696581199999999,
				"int_h": 36,
				"int_w": 101,
				"int_x": 877,
				"int_y": 136,
				"w": 0.05643340860000001,
				"x": 0.49503386000000005,
				"y": 0.1451923077
			}
		},
		{
			"class_idx": 0,
			"name": "license-plate",
			"points": [
				{
					"int_x": 1160,
					"int_y": 281,
					"x": 0.6545711061,
					"y": 0.30010683755
				},
				{
					"int_x": 1176,
					"int_y": 281,
					"x": 0.6634875847,
					"y": 0.30010683755
				},
				{
					"int_x": 1176,
					"int_y": 287,
					"x": 0.6634875847,
					"y": 0.30715811964999995
				},
				{
					"int_x": 1160,
					"int_y": 287,
					"x": 0.6545711061,
					"y": 0.30715811964999995
				}
			],
			"rect": {
				"h": 0.007051282099999945,
				"int_h": 7,
				"int_w": 17,
				"int_x": 1160,
				"int_y": 281,
				"w": 0.0089164786,
				"x": 0.6545711061,
				"y": 0.30010683755
			}
		}
	],
	"timestamp": 1722547379,
	"version": "1.8.27-1"
}
