{
	"completely_empty": false,
	"image": {
		"height": 940,
		"scale": 0.6920950801547816,
		"width": 1809
	},
	"mark": [
		{
			"class_idx": 0,
			"name": "license-plate",
			"points": [
				{
					"int_x": 814,
					"int_y": 698,
					"x": 0.4501381978993919,
					"y": 0.7425531914893617
				},
				{
					"int_x": 884,
					"int_y": 698,
					"x": 0.4887230514096186,
					"y": 0.7425531914893617
				},
				{
					"int_x": 884,
					"int_y": 731,
					"x": 0.4887230514096186,
					"y": 0.7778723404255319
				},
				{
					"int_x": 814,
					"int_y": 731,
					"x": 0.4501381978993919,
					"y": 0.7778723404255319
				}
			],
			"rect": {
				"h": 0.035319148936170164,
				"int_h": 34,
				"int_w": 71,
				"int_x": 814,
				"int_y": 698,
				"w": 0.03858485351022667,
				"x": 0.4501381978993919,
				"y": 0.7425531914893617
			}
		}
	],
	"timestamp": 1720926690,
	"version": "1.8.27-1"
}
