{
	"completely_empty": false,
	"image": {
		"height": 602,
		"scale": 1.1445477599323752,
		"width": 1183
	},
	"mark": [
		{
			"class_idx": 0,
			"name": "license-plate",
			"points": [
				{
					"int_x": 961,
					"int_y": 128,
					"x": 0.81242603555,
					"y": 0.2127906977
				},
				{
					"int_x": 1009,
					"int_y": 128,
					"x": 0.85316990705,
					"y": 0.2127906977
				},
				{
					"int_x": 1009,
					"int_y": 153,
					"x": 0.85316990705,
					"y": 0.2536544851
				},
				{
					"int_x": 961,
					"int_y": 153,
					"x": 0.81242603555,
					"y": 0.2536544851
				}
			],
			"rect": {
				"h": 0.04086378739999999,
				"int_h": 26,
				"int_w": 49,
				"int_x": 961,
				"int_y": 128,
				"w": 0.04074387149999992,
				"x": 0.81242603555,
				"y": 0.2127906977
			}
		},
		{
			"class_idx": 0,
			"name": "license-plate",
			"points": [
				{
					"int_x": 392,
					"int_y": 190,
					"x": 0.33153000845,
					"y": 0.31627906969999997
				},
				{
					"int_x": 432,
					"int_y": 190,
					"x": 0.36500422655,
					"y": 0.31627906969999997
				},
				{
					"int_x": 432,
					"int_y": 210,
					"x": 0.36500422655,
					"y": 0.3495016611
				},
				{
					"int_x": 392,
					"int_y": 210,
					"x": 0.33153000845,
					"y": 0.3495016611
				}
			],
			"rect": {
				"h": 0.03322259140000006,
				"int_h": 21,
				"int_w": 41,
				"int_x": 392,
				"int_y": 190,
				"w": 0.03347421809999995,
				"x": 0.33153000845,
				"y": 0.31627906969999997
			}
		},
		{
			"class_idx": 0,
			"name": "license-plate",
			"points": [
				{
					"int_x": 615,
					"int_y": 223,
					"x": 0.52028740485,
					"y": 0.37093023255
				},
				{
					"int_x": 631,
					"int_y": 223,
					"x": 0.53364327975,
					"y": 0.37093023255
				},
				{
					"int_x": 631,
					"int_y": 232,
					"x": 0.53364327975,
					"y": 0.38588039865
				},
				{
					"int_x": 615,
					"int_y": 232,
					"x": 0.52028740485,
					"y": 0.38588039865
				}
			],
			"rect": {
				"h": 0.014950166099999995,
				"int_h": 10,
				"int_w": 17,
				"int_x": 615,
				"int_y": 223,
				"w": 0.013355874900000009,
				"x": 0.52028740485,
				"y": 0.37093023255
			}
		}
	],
	"timestamp": 1722547418,
	"version": "1.8.27-1"
}
