{
	"completely_empty": false,
	"image": {
		"height": 1232,
		"scale": 0.5641233766233766,
		"width": 827
	},
	"mark": [
		{
			"class_idx": 0,
			"name": "license-plate",
			"points": [
				{
					"int_x": 598,
					"int_y": 571,
					"x": 0.7234582829,
					"y": 0.46331168829999997
				},
				{
					"int_x": 620,
					"int_y": 571,
					"x": 0.7498186215,
					"y": 0.46331168829999997
				},
				{
					"int_x": 620,
					"int_y": 615,
					"x": 0.7498186215,
					"y": 0.4993506493
				},
				{
					"int_x": 598,
					"int_y": 615,
					"x": 0.7234582829,
					"y": 0.4993506493
				}
			],
			"rect": {
				"h": 0.036038961000000036,
				"int_h": 45,
				"int_w": 23,
				"int_x": 598,
				"int_y": 571,
				"w": 0.026360338599999977,
				"x": 0.7234582829,
				"y": 0.46331168829999997
			}
		}
	],
	"timestamp": 1722547397,
	"version": "1.8.27-1"
}
