{
	"completely_empty": false,
	"image": {
		"height": 1179,
		"scale": 0.5894826123833757,
		"width": 1728
	},
	"mark": [
		{
			"class_idx": 0,
			"name": "license-plate",
			"points": [
				{
					"int_x": 961,
					"int_y": 309,
					"x": 0.5561921297,
					"y": 0.2622561493
				},
				{
					"int_x": 1011,
					"int_y": 309,
					"x": 0.5850115741,
					"y": 0.2622561493
				},
				{
					"int_x": 1011,
					"int_y": 330,
					"x": 0.5850115741,
					"y": 0.2795589483
				},
				{
					"int_x": 961,
					"int_y": 330,
					"x": 0.5561921297,
					"y": 0.2795589483
				}
			],
			"rect": {
				"h": 0.01730279899999998,
				"int_h": 22,
				"int_w": 51,
				"int_x": 961,
				"int_y": 309,
				"w": 0.02881944440000006,
				"x": 0.5561921297,
				"y": 0.2622561493
			}
		}
	],
	"timestamp": 1722547396,
	"version": "1.8.27-1"
}
