{
	"completely_empty": false,
	"image": {
		"height": 714,
		"scale": 0.966452533904354,
		"width": 1401
	},
	"mark": [
		{
			"class_idx": 0,
			"name": "license-plate",
			"points": [
				{
					"int_x": 933,
					"int_y": 182,
					"x": 0.6659528908,
					"y": 0.25462184875
				},
				{
					"int_x": 1014,
					"int_y": 182,
					"x": 0.7239114917999999,
					"y": 0.25462184875
				},
				{
					"int_x": 1014,
					"int_y": 200,
					"x": 0.7239114917999999,
					"y": 0.28039215685
				},
				{
					"int_x": 933,
					"int_y": 200,
					"x": 0.6659528908,
					"y": 0.28039215685
				}
			],
			"rect": {
				"h": 0.025770308100000028,
				"int_h": 19,
				"int_w": 82,
				"int_x": 933,
				"int_y": 182,
				"w": 0.05795860099999994,
				"x": 0.6659528908,
				"y": 0.25462184875
			}
		}
	],
	"timestamp": 1722547405,
	"version": "1.8.27-1"
}
