{
	"completely_empty": false,
	"image": {
		"height": 1626,
		"scale": 0.4274292742927429,
		"width": 795
	},
	"mark": [
		{
			"class_idx": 0,
			"name": "license-plate",
			"points": [
				{
					"int_x": 550,
					"int_y": 333,
					"x": 0.69132075475,
					"y": 0.20479704799999998
				},
				{
					"int_x": 577,
					"int_y": 333,
					"x": 0.72553459125,
					"y": 0.20479704799999998
				},
				{
					"int_x": 577,
					"int_y": 403,
					"x": 0.72553459125,
					"y": 0.248093481
				},
				{
					"int_x": 550,
					"int_y": 403,
					"x": 0.69132075475,
					"y": 0.248093481
				}
			],
			"rect": {
				"h": 0.04329643300000002,
				"int_h": 71,
				"int_w": 28,
				"int_x": 550,
				"int_y": 333,
				"w": 0.03421383649999998,
				"x": 0.69132075475,
				"y": 0.20479704799999998
			}
		},
		{
			"class_idx": 0,
			"name": "license-plate",
			"points": [
				{
					"int_x": 552,
					"int_y": 428,
					"x": 0.6944654088000001,
					"y": 0.2633456334
				},
				{
					"int_x": 578,
					"int_y": 428,
					"x": 0.7274213836,
					"y": 0.2633456334
				},
				{
					"int_x": 578,
					"int_y": 499,
					"x": 0.7274213836,
					"y": 0.30664206639999997
				},
				{
					"int_x": 552,
					"int_y": 499,
					"x": 0.6944654088000001,
					"y": 0.30664206639999997
				}
			],
			"rect": {
				"h": 0.04329643299999997,
				"int_h": 72,
				"int_w": 27,
				"int_x": 552,
				"int_y": 428,
				"w": 0.0329559747999999,
				"x": 0.6944654088000001,
				"y": 0.2633456334
			}
		}
	],
	"timestamp": 1722547404,
	"version": "1.8.27-1"
}
