{
	"completely_empty": false,
	"image": {
		"height": 1613,
		"scale": 0.43087414755114695,
		"width": 843
	},
	"mark": [
		{
			"class_idx": 0,
			"name": "license-plate",
			"points": [
				{
					"int_x": 141,
					"int_y": 285,
					"x": 0.16737841039999998,
					"y": 0.17693738375
				},
				{
					"int_x": 162,
					"int_y": 285,
					"x": 0.1918149466,
					"y": 0.17693738375
				},
				{
					"int_x": 162,
					"int_y": 341,
					"x": 0.1918149466,
					"y": 0.21165530065
				},
				{
					"int_x": 141,
					"int_y": 341,
					"x": 0.16737841039999998,
					"y": 0.21165530065
				}
			],
			"rect": {
				"h": 0.03471791689999998,
				"int_h": 57,
				"int_w": 22,
				"int_x": 141,
				"int_y": 285,
				"w": 0.024436536200000025,
				"x": 0.16737841039999998,
				"y": 0.17693738375
			}
		}
	],
	"timestamp": 1722547403,
	"version": "1.8.27-1"
}
