{
	"completely_empty": false,
	"image": {
		"height": 1639,
		"scale": 0.424039048200122,
		"width": 781
	},
	"mark": [
		{
			"class_idx": 0,
			"name": "license-plate",
			"points": [
				{
					"int_x": 292,
					"int_y": 373,
					"x": 0.37323943665,
					"y": 0.2274557657
				},
				{
					"int_x": 302,
					"int_y": 373,
					"x": 0.38681177975,
					"y": 0.2274557657
				},
				{
					"int_x": 302,
					"int_y": 418,
					"x": 0.38681177975,
					"y": 0.2552776083
				},
				{
					"int_x": 292,
					"int_y": 418,
					"x": 0.37323943665,
					"y": 0.2552776083
				}
			],
			"rect": {
				"h": 0.027821842600000007,
				"int_h": 46,
				"int_w": 11,
				"int_x": 292,
				"int_y": 373,
				"w": 0.013572343099999995,
				"x": 0.37323943665,
				"y": 0.2274557657
			}
		}
	],
	"timestamp": 1722547405,
	"version": "1.8.27-1"
}
