{
	"completely_empty": false,
	"image": {
		"height": 613,
		"scale": 1.133768352365416,
		"width": 977
	},
	"mark": [
		{
			"class_idx": 0,
			"name": "license-plate",
			"points": [
				{
					"int_x": 461,
					"int_y": 357,
					"x": 0.4721596724667349,
					"y": 0.5825448613376836
				},
				{
					"int_x": 500,
					"int_y": 357,
					"x": 0.5120777891504606,
					"y": 0.5825448613376836
				},
				{
					"int_x": 500,
					"int_y": 371,
					"x": 0.5120777891504606,
					"y": 0.6050570962479609
				},
				{
					"int_x": 461,
					"int_y": 371,
					"x": 0.4721596724667349,
					"y": 0.6050570962479609
				}
			],
			"rect": {
				"h": 0.022512234910277318,
				"int_h": 15,
				"int_w": 40,
				"int_x": 461,
				"int_y": 357,
				"w": 0.039918116683725746,
				"x": 0.4721596724667349,
				"y": 0.5825448613376836
			}
		}
	],
	"timestamp": 1721085890,
	"version": "1.8.27-1"
}
