{
	"completely_empty": false,
	"image": {
		"height": 718,
		"scale": 0.9229720518064076,
		"width": 1467
	},
	"mark": [
		{
			"class_idx": 0,
			"name": "license-plate",
			"points": [
				{
					"int_x": 97,
					"int_y": 258,
					"x": 0.0663940014,
					"y": 0.35919220059999996
				},
				{
					"int_x": 169,
					"int_y": 258,
					"x": 0.11492842539999999,
					"y": 0.35919220059999996
				},
				{
					"int_x": 169,
					"int_y": 296,
					"x": 0.11492842539999999,
					"y": 0.4123955432
				},
				{
					"int_x": 97,
					"int_y": 296,
					"x": 0.0663940014,
					"y": 0.4123955432
				}
			],
			"rect": {
				"h": 0.053203342600000036,
				"int_h": 39,
				"int_w": 73,
				"int_x": 97,
				"int_y": 258,
				"w": 0.04853442399999999,
				"x": 0.0663940014,
				"y": 0.35919220059999996
			}
		},
		{
			"class_idx": 0,
			"name": "license-plate",
			"points": [
				{
					"int_x": 624,
					"int_y": 358,
					"x": 0.42515337425,
					"y": 0.498189415
				},
				{
					"int_x": 672,
					"int_y": 358,
					"x": 0.45800954335,
					"y": 0.498189415
				},
				{
					"int_x": 672,
					"int_y": 376,
					"x": 0.45800954335,
					"y": 0.5229805014000001
				},
				{
					"int_x": 624,
					"int_y": 376,
					"x": 0.42515337425,
					"y": 0.5229805014000001
				}
			],
			"rect": {
				"h": 0.02479108640000005,
				"int_h": 19,
				"int_w": 49,
				"int_x": 624,
				"int_y": 358,
				"w": 0.0328561691,
				"x": 0.42515337425,
				"y": 0.498189415
			}
		},
		{
			"class_idx": 0,
			"name": "license-plate",
			"points": [
				{
					"int_x": 1186,
					"int_y": 493,
					"x": 0.8083844581,
					"y": 0.6867688022
				},
				{
					"int_x": 1205,
					"int_y": 493,
					"x": 0.8216087253000001,
					"y": 0.6867688022
				},
				{
					"int_x": 1205,
					"int_y": 500,
					"x": 0.8216087253000001,
					"y": 0.6965181058000001
				},
				{
					"int_x": 1186,
					"int_y": 500,
					"x": 0.8083844581,
					"y": 0.6965181058000001
				}
			],
			"rect": {
				"h": 0.009749303600000037,
				"int_h": 8,
				"int_w": 20,
				"int_x": 1186,
				"int_y": 493,
				"w": 0.013224267200000028,
				"x": 0.8083844581,
				"y": 0.6867688022
			}
		}
	],
	"timestamp": 1722547077,
	"version": "1.8.27-1"
}
