{
	"completely_empty": false,
	"image": {
		"height": 1705,
		"scale": 0.40762463343108507,
		"width": 761
	},
	"mark": [
		{
			"class_idx": 0,
			"name": "license-plate",
			"points": [
				{
					"int_x": 596,
					"int_y": 133,
					"x": 0.78265440215,
					"y": 0.0781818182
				},
				{
					"int_x": 627,
					"int_y": 133,
					"x": 0.8241787122500001,
					"y": 0.0781818182
				},
				{
					"int_x": 627,
					"int_y": 196,
					"x": 0.8241787122500001,
					"y": 0.11513196479999999
				},
				{
					"int_x": 596,
					"int_y": 196,
					"x": 0.78265440215,
					"y": 0.11513196479999999
				}
			],
			"rect": {
				"h": 0.03695014659999998,
				"int_h": 64,
				"int_w": 32,
				"int_x": 596,
				"int_y": 133,
				"w": 0.04152431010000002,
				"x": 0.78265440215,
				"y": 0.0781818182
			}
		},
		{
			"class_idx": 0,
			"name": "license-plate",
			"points": [
				{
					"int_x": 515,
					"int_y": 1473,
					"x": 0.6772667542999999,
					"y": 0.8638709677
				},
				{
					"int_x": 542,
					"int_y": 1473,
					"x": 0.7124835743,
					"y": 0.8638709677
				},
				{
					"int_x": 542,
					"int_y": 1532,
					"x": 0.7124835743,
					"y": 0.8984750733
				},
				{
					"int_x": 515,
					"int_y": 1532,
					"x": 0.6772667542999999,
					"y": 0.8984750733
				}
			],
			"rect": {
				"h": 0.034604105599999935,
				"int_h": 60,
				"int_w": 28,
				"int_x": 515,
				"int_y": 1473,
				"w": 0.03521682000000004,
				"x": 0.6772667542999999,
				"y": 0.8638709677
			}
		}
	],
	"timestamp": 1722547374,
	"version": "1.8.27-1"
}
