{
	"completely_empty": false,
	"image": {
		"height": 754,
		"scale": 0.9185888738127544,
		"width": 1474
	},
	"mark": [
		{
			"class_idx": 0,
			"name": "license-plate",
			"points": [
				{
					"int_x": 861,
					"int_y": 266,
					"x": 0.5839328537499999,
					"y": 0.353125
				},
				{
					"int_x": 904,
					"int_y": 266,
					"x": 0.61350919265,
					"y": 0.353125
				},
				{
					"int_x": 904,
					"int_y": 283,
					"x": 0.61350919265,
					"y": 0.375
				},
				{
					"int_x": 861,
					"int_y": 283,
					"x": 0.5839328537499999,
					"y": 0.375
				}
			],
			"rect": {
				"h": 0.021874999999999978,
				"int_h": 18,
				"int_w": 44,
				"int_x": 861,
				"int_y": 266,
				"w": 0.02957633890000011,
				"x": 0.5839328537499999,
				"y": 0.353125
			}
		},
		{
			"class_idx": 0,
			"name": "license-plate",
			"points": [
				{
					"int_x": 952,
					"int_y": 313,
					"x": 0.6460494811999999,
					"y": 0.4153666147
				},
				{
					"int_x": 966,
					"int_y": 313,
					"x": 0.6556264964,
					"y": 0.4153666147
				},
				{
					"int_x": 966,
					"int_y": 321,
					"x": 0.6556264964,
					"y": 0.4255070203
				},
				{
					"int_x": 952,
					"int_y": 321,
					"x": 0.6460494811999999,
					"y": 0.4255070203
				}
			],
			"rect": {
				"h": 0.010140405599999958,
				"int_h": 9,
				"int_w": 15,
				"int_x": 952,
				"int_y": 313,
				"w": 0.009577015200000094,
				"x": 0.6460494811999999,
				"y": 0.4153666147
			}
		},
		{
			"class_idx": 0,
			"name": "license-plate",
			"points": [
				{
					"int_x": 1189,
					"int_y": 286,
					"x": 0.8069544364500001,
					"y": 0.37890625
				},
				{
					"int_x": 1207,
					"int_y": 286,
					"x": 0.81894484415,
					"y": 0.37890625
				},
				{
					"int_x": 1207,
					"int_y": 299,
					"x": 0.81894484415,
					"y": 0.39609375
				},
				{
					"int_x": 1189,
					"int_y": 299,
					"x": 0.8069544364500001,
					"y": 0.39609375
				}
			],
			"rect": {
				"h": 0.017187500000000022,
				"int_h": 14,
				"int_w": 19,
				"int_x": 1189,
				"int_y": 286,
				"w": 0.011990407699999928,
				"x": 0.8069544364500001,
				"y": 0.37890625
			}
		},
		{
			"class_idx": 0,
			"name": "license-plate",
			"points": [
				{
					"int_x": 585,
					"int_y": 342,
					"x": 0.397047087,
					"y": 0.45358814350000004
				},
				{
					"int_x": 599,
					"int_y": 342,
					"x": 0.4066241022,
					"y": 0.45358814350000004
				},
				{
					"int_x": 599,
					"int_y": 352,
					"x": 0.4066241022,
					"y": 0.4668486739
				},
				{
					"int_x": 585,
					"int_y": 352,
					"x": 0.397047087,
					"y": 0.4668486739
				}
			],
			"rect": {
				"h": 0.01326053039999997,
				"int_h": 11,
				"int_w": 15,
				"int_x": 585,
				"int_y": 342,
				"w": 0.009577015199999983,
				"x": 0.397047087,
				"y": 0.45358814350000004
			}
		}
	],
	"timestamp": 1722547070,
	"version": "1.8.27-1"
}
