{
	"completely_empty": false,
	"image": {
		"height": 779,
		"scale": 0.6986584107327142,
		"width": 1938
	},
	"mark": [
		{
			"class_idx": 0,
			"name": "license-plate",
			"points": [
				{
					"int_x": 208,
					"int_y": 140,
					"x": 0.10706914349999999,
					"y": 0.179589217
				},
				{
					"int_x": 307,
					"int_y": 140,
					"x": 0.1585655315,
					"y": 0.179589217
				},
				{
					"int_x": 307,
					"int_y": 195,
					"x": 0.1585655315,
					"y": 0.2501925546
				},
				{
					"int_x": 208,
					"int_y": 195,
					"x": 0.10706914349999999,
					"y": 0.2501925546
				}
			],
			"rect": {
				"h": 0.07060333760000001,
				"int_h": 56,
				"int_w": 100,
				"int_x": 208,
				"int_y": 140,
				"w": 0.051496388000000004,
				"x": 0.10706914349999999,
				"y": 0.179589217
			}
		},
		{
			"class_idx": 0,
			"name": "license-plate",
			"points": [
				{
					"int_x": 1657,
					"int_y": 234,
					"x": 0.8550567595,
					"y": 0.30064184850000003
				},
				{
					"int_x": 1745,
					"int_y": 234,
					"x": 0.9003611971000001,
					"y": 0.30064184850000003
				},
				{
					"int_x": 1745,
					"int_y": 268,
					"x": 0.9003611971000001,
					"y": 0.3442875481
				},
				{
					"int_x": 1657,
					"int_y": 268,
					"x": 0.8550567595,
					"y": 0.3442875481
				}
			],
			"rect": {
				"h": 0.043645699599999976,
				"int_h": 35,
				"int_w": 89,
				"int_x": 1657,
				"int_y": 234,
				"w": 0.045304437600000025,
				"x": 0.8550567595,
				"y": 0.30064184850000003
			}
		},
		{
			"class_idx": 0,
			"name": "license-plate",
			"points": [
				{
					"int_x": 1353,
					"int_y": 489,
					"x": 0.698245614,
					"y": 0.6275994865
				},
				{
					"int_x": 1370,
					"int_y": 489,
					"x": 0.7071207429999999,
					"y": 0.6275994865
				},
				{
					"int_x": 1370,
					"int_y": 497,
					"x": 0.7071207429999999,
					"y": 0.6381258022999999
				},
				{
					"int_x": 1353,
					"int_y": 497,
					"x": 0.698245614,
					"y": 0.6381258022999999
				}
			],
			"rect": {
				"h": 0.010526315799999963,
				"int_h": 9,
				"int_w": 18,
				"int_x": 1353,
				"int_y": 489,
				"w": 0.008875128999999982,
				"x": 0.698245614,
				"y": 0.6275994865
			}
		},
		{
			"class_idx": 0,
			"name": "license-plate",
			"points": [
				{
					"int_x": 833,
					"int_y": 503,
					"x": 0.42977296185,
					"y": 0.6462130937499999
				},
				{
					"int_x": 848,
					"int_y": 503,
					"x": 0.43751289995,
					"y": 0.6462130937499999
				},
				{
					"int_x": 848,
					"int_y": 511,
					"x": 0.43751289995,
					"y": 0.65545571245
				},
				{
					"int_x": 833,
					"int_y": 511,
					"x": 0.42977296185,
					"y": 0.65545571245
				}
			],
			"rect": {
				"h": 0.009242618700000094,
				"int_h": 9,
				"int_w": 16,
				"int_x": 833,
				"int_y": 503,
				"w": 0.0077399380999999545,
				"x": 0.42977296185,
				"y": 0.6462130937499999
			}
		},
		{
			"class_idx": 0,
			"name": "license-plate",
			"points": [
				{
					"int_x": 1014,
					"int_y": 511,
					"x": 0.52301341595,
					"y": 0.6564826700999999
				},
				{
					"int_x": 1031,
					"int_y": 511,
					"x": 0.53209494325,
					"y": 0.6564826700999999
				},
				{
					"int_x": 1031,
					"int_y": 521,
					"x": 0.53209494325,
					"y": 0.6682926829
				},
				{
					"int_x": 1014,
					"int_y": 521,
					"x": 0.52301341595,
					"y": 0.6682926829
				}
			],
			"rect": {
				"h": 0.011810012800000047,
				"int_h": 11,
				"int_w": 18,
				"int_x": 1014,
				"int_y": 511,
				"w": 0.009081527300000003,
				"x": 0.52301341595,
				"y": 0.6564826700999999
			}
		},
		{
			"class_idx": 0,
			"name": "license-plate",
			"points": [
				{
					"int_x": 1103,
					"int_y": 518,
					"x": 0.56893704855,
					"y": 0.66546854945
				},
				{
					"int_x": 1116,
					"int_y": 518,
					"x": 0.57574819405,
					"y": 0.66546854945
				},
				{
					"int_x": 1116,
					"int_y": 525,
					"x": 0.57574819405,
					"y": 0.6736842105499999
				},
				{
					"int_x": 1103,
					"int_y": 525,
					"x": 0.56893704855,
					"y": 0.6736842105499999
				}
			],
			"rect": {
				"h": 0.008215661099999938,
				"int_h": 8,
				"int_w": 14,
				"int_x": 1103,
				"int_y": 518,
				"w": 0.006811145499999949,
				"x": 0.56893704855,
				"y": 0.66546854945
			}
		},
		{
			"class_idx": 0,
			"name": "license-plate",
			"points": [
				{
					"int_x": 1233,
					"int_y": 518,
					"x": 0.6364293086,
					"y": 0.6649550706
				},
				{
					"int_x": 1247,
					"int_y": 518,
					"x": 0.6436532508,
					"y": 0.6649550706
				},
				{
					"int_x": 1247,
					"int_y": 526,
					"x": 0.6436532508,
					"y": 0.6747111682
				},
				{
					"int_x": 1233,
					"int_y": 526,
					"x": 0.6364293086,
					"y": 0.6747111682
				}
			],
			"rect": {
				"h": 0.009756097599999958,
				"int_h": 9,
				"int_w": 15,
				"int_x": 1233,
				"int_y": 518,
				"w": 0.0072239422,
				"x": 0.6364293086,
				"y": 0.6649550706
			}
		},
		{
			"class_idx": 0,
			"name": "license-plate",
			"points": [
				{
					"int_x": 1797,
					"int_y": 496,
					"x": 0.92708978325,
					"y": 0.63722721435
				},
				{
					"int_x": 1817,
					"int_y": 496,
					"x": 0.93730650155,
					"y": 0.63722721435
				},
				{
					"int_x": 1817,
					"int_y": 503,
					"x": 0.93730650155,
					"y": 0.64595635425
				},
				{
					"int_x": 1797,
					"int_y": 503,
					"x": 0.92708978325,
					"y": 0.64595635425
				}
			],
			"rect": {
				"h": 0.008729139900000016,
				"int_h": 8,
				"int_w": 21,
				"int_x": 1797,
				"int_y": 496,
				"w": 0.010216718299999927,
				"x": 0.92708978325,
				"y": 0.63722721435
			}
		}
	],
	"timestamp": 1722547078,
	"version": "1.8.27-1"
}
