{
	"completely_empty": false,
	"image": {
		"height": 881,
		"scale": 0.704474505723205,
		"width": 1922
	},
	"mark": [
		{
			"class_idx": 0,
			"name": "license-plate",
			"points": [
				{
					"int_x": 122,
					"int_y": 63,
					"x": 0.06373569194999999,
					"y": 0.07162315555000001
				},
				{
					"int_x": 204,
					"int_y": 63,
					"x": 0.10629552545,
					"y": 0.07162315555000001
				},
				{
					"int_x": 204,
					"int_y": 126,
					"x": 0.10629552545,
					"y": 0.14313280365
				},
				{
					"int_x": 122,
					"int_y": 126,
					"x": 0.06373569194999999,
					"y": 0.14313280365
				}
			],
			"rect": {
				"h": 0.07150964809999999,
				"int_h": 64,
				"int_w": 83,
				"int_x": 122,
				"int_y": 63,
				"w": 0.042559833500000005,
				"x": 0.06373569194999999,
				"y": 0.07162315555000001
			}
		},
		{
			"class_idx": 0,
			"name": "license-plate",
			"points": [
				{
					"int_x": 1571,
					"int_y": 214,
					"x": 0.8174817898,
					"y": 0.24324631105
				},
				{
					"int_x": 1658,
					"int_y": 214,
					"x": 0.8624349635999999,
					"y": 0.24324631105
				},
				{
					"int_x": 1658,
					"int_y": 259,
					"x": 0.8624349635999999,
					"y": 0.29432463115
				},
				{
					"int_x": 1571,
					"int_y": 259,
					"x": 0.8174817898,
					"y": 0.29432463115
				}
			],
			"rect": {
				"h": 0.05107832010000002,
				"int_h": 46,
				"int_w": 88,
				"int_x": 1571,
				"int_y": 214,
				"w": 0.04495317379999997,
				"x": 0.8174817898,
				"y": 0.24324631105
			}
		},
		{
			"class_idx": 0,
			"name": "license-plate",
			"points": [
				{
					"int_x": 832,
					"int_y": 476,
					"x": 0.4330385015,
					"y": 0.5402951192000001
				},
				{
					"int_x": 851,
					"int_y": 476,
					"x": 0.4427159209,
					"y": 0.5402951192000001
				},
				{
					"int_x": 851,
					"int_y": 484,
					"x": 0.4427159209,
					"y": 0.549829739
				},
				{
					"int_x": 832,
					"int_y": 484,
					"x": 0.4330385015,
					"y": 0.549829739
				}
			],
			"rect": {
				"h": 0.009534619799999922,
				"int_h": 9,
				"int_w": 20,
				"int_x": 832,
				"int_y": 476,
				"w": 0.009677419399999998,
				"x": 0.4330385015,
				"y": 0.5402951192000001
			}
		}
	],
	"timestamp": 1722547376,
	"version": "1.8.27-1"
}
