{
	"completely_empty": false,
	"image": {
		"height": 1424,
		"scale": 0.488061797752809,
		"width": 631
	},
	"mark": [
		{
			"class_idx": 0,
			"name": "license-plate",
			"points": [
				{
					"int_x": 72,
					"int_y": 1233,
					"x": 0.11378763859999999,
					"y": 0.86587078655
				},
				{
					"int_x": 108,
					"int_y": 1233,
					"x": 0.17147385099999998,
					"y": 0.86587078655
				},
				{
					"int_x": 108,
					"int_y": 1288,
					"x": 0.17147385099999998,
					"y": 0.90463483145
				},
				{
					"int_x": 72,
					"int_y": 1288,
					"x": 0.11378763859999999,
					"y": 0.90463483145
				}
			],
			"rect": {
				"h": 0.03876404489999996,
				"int_h": 56,
				"int_w": 37,
				"int_x": 72,
				"int_y": 1233,
				"w": 0.05768621239999999,
				"x": 0.11378763859999999,
				"y": 0.86587078655
			}
		}
	],
	"timestamp": 1722547073,
	"version": "1.8.27-1"
}
